ws/__init__.py
ws/adt.py
ws/alg.py
ws/common.py
ws/download.py
ws/pdict.py
ws/render.py
ws/services.py
ws/settings.py
ws/xpath.py
ws-0.3.1.dist-info/licenses/LICENSE
ws-0.3.1.dist-info/METADATA
ws-0.3.1.dist-info/WHEEL
ws-0.3.1.dist-info/top_level.txt
ws-0.3.1.dist-info/RECORD
