Metadata-Version: 2.4
Name: ws
Version: 0.3.1
Summary: Efficient asyncio based web crawler
Author-email: Richard Penman <richard.penman@gmail.com>
License:                   GNU LESSER GENERAL PUBLIC LICENSE
Project-URL: Homepage, https://github.com/richardpenman/ws
Classifier: License :: OSI Approved :: GNU Library or Lesser General Public License (LGPL)
Classifier: Programming Language :: Python :: 3
Requires-Python: >=3.9
License-File: LICENSE
Requires-Dist: lxml==5.2.2
Requires-Dist: requests==2.32.3
Requires-Dist: selenium==4.22.0
Dynamic: license-file
